my_weather_package/__init__.py
my_weather_package/__main__.py
my_weather_package/city.py
my_weather_package/weather.py
my_weather_package-0.1.0.3.dist-info/DESCRIPTION.rst
my_weather_package-0.1.0.3.dist-info/METADATA
my_weather_package-0.1.0.3.dist-info/RECORD
my_weather_package-0.1.0.3.dist-info/WHEEL
my_weather_package-0.1.0.3.dist-info/entry_points.txt
my_weather_package-0.1.0.3.dist-info/metadata.json
my_weather_package-0.1.0.3.dist-info/top_level.txt
