Metadata-Version: 2.0
Name: my-weather-package
Version: 0.1.0.3
Summary: A sample Python project for weather information
Home-page: https://git.corp.adobe.com/fulgeanu/weather-module.git
Author: Ioan Fulgeanu
Author-email: fulgeanu.ioan@gmail.com
License: MIT
Keywords: sample setuptools development
Platform: UNKNOWN
Classifier: Development Status :: 3 - Alpha
Classifier: Intended Audience :: Developers
Classifier: Topic :: Software Development :: Build Tools
Classifier: License :: OSI Approved :: MIT License
Classifier: Programming Language :: Python :: 2.7
